Metadata-Version: 1.0
Name: spyer
Version: 0.0.1
Summary:  麻瓜编程
Home-page: https://opslinux.com
Author: ce
Author-email: zbing3@163.com
License: UNKNOWN
Platform: UNKNOWN
